cosmos_api/__init__.py
pycosmosapi-0.0.3.dist-info/LICENSE
pycosmosapi-0.0.3.dist-info/METADATA
pycosmosapi-0.0.3.dist-info/WHEEL
pycosmosapi-0.0.3.dist-info/top_level.txt
pycosmosapi-0.0.3.dist-info/RECORD
