Metadata-Version: 2.1
Name: pycosmosapi
Version: 0.0.3
Summary: Telemetry helper for Cosmos API.
Home-page: https://dmtest.cosmos.ali.jp/docapi
Author: A.L.I Technologies
Author-email: benjamin.ioller@ali.jp
License: Apache 2.0
Keywords: cosmos,pycosmos
Platform: UNKNOWN
Requires-Python: >=3.5
Requires-Dist: requests (>=2.23.0)
